lektor_netlify_redirects.py
lektor_netlify_redirects-0.2.dist-info/DESCRIPTION.rst
lektor_netlify_redirects-0.2.dist-info/METADATA
lektor_netlify_redirects-0.2.dist-info/RECORD
lektor_netlify_redirects-0.2.dist-info/WHEEL
lektor_netlify_redirects-0.2.dist-info/entry_points.txt
lektor_netlify_redirects-0.2.dist-info/metadata.json
lektor_netlify_redirects-0.2.dist-info/top_level.txt
