Metadata-Version: 2.0
Name: lektor-netlify-redirects
Version: 0.2
Summary: A basic application for redirects in netlify
Home-page: https://daredoes.work
Author: DareDoes
Author-email: me@daredoes.work
License: MIT
Platform: UNKNOWN
